barr4/__init__.py
barr4/core.py
barr4crypt-0.2.2.dist-info/LICENSE
barr4crypt-0.2.2.dist-info/METADATA
barr4crypt-0.2.2.dist-info/WHEEL
barr4crypt-0.2.2.dist-info/top_level.txt
barr4crypt-0.2.2.dist-info/RECORD
