Metadata-Version: 2.1
Name: barr4crypt
Version: 0.2.2
Summary: A simple rotation-based encryption tool
Home-page: https://github.com/francool57/barr4encrypt
Author: Francisco Barreira
Author-email: franbarreira0@gmail.com
Classifier: Development Status :: 3 - Alpha
Classifier: Intended Audience :: Developers
Classifier: License :: OSI Approved :: MIT License
Classifier: Operating System :: OS Independent
Classifier: Programming Language :: Python :: 3
Classifier: Programming Language :: Python :: 3.6
Classifier: Programming Language :: Python :: 3.7
Classifier: Programming Language :: Python :: 3.8
Classifier: Programming Language :: Python :: 3.9
Requires-Python: >=3.6
License-File: LICENSE
